{
  "project_info": {
    "project_number": "290159247030",
    "project_id": "fruitmobile-31368",
    "storage_bucket": "fruitmobile-31368.firebasestorage.app"
  },
  "client": [
    {
      "client_info": {
        "mobilesdk_app_id": "1:290159247030:android:e9bb86d7f4fc888a9a3017",
        "android_client_info": {
          "package_name": "com.example.flutter_application_6"
        }
      },
      "oauth_client": [],
      "api_key": [
        {
          "current_key": "AIzaSyDYKRsLY-ko3kGGUsQAwwmcxkh_-HO9lFQ"
        }
      ],
      "services": {
        "appinvite_service": {
          "other_platform_oauth_client": []
        }
      }
    }
  ],
  "configuration_version": "1"
}